kinetics/__init__.py
kinetics/model_module.py
kinetics/optimisation/__init__.py
kinetics/optimisation/genetic_algorithm.py
kinetics/optimisation/metrics.py
kinetics/other_analysis/__init__.py
kinetics/other_analysis/initial_rates.py
kinetics/reaction_classes/__init__.py
kinetics/reaction_classes/equilibrium_mass_action.py
kinetics/reaction_classes/equilibrium_reversible_mechaelis_menton.py
kinetics/reaction_classes/general_rate_Law.py
kinetics/reaction_classes/irreversible_michaelis_menton.py
kinetics/reaction_classes/mass_transfer.py
kinetics/reaction_classes/michaelis_menton_modifiers.py
kinetics/reaction_classes/reaction_base_class.py
kinetics/reaction_classes/reversible_michaelis_menton.py
kinetics/reaction_classes/thermodynamic_separable_rate_law.py
kinetics/ua_and_sa/__init__.py
kinetics/ua_and_sa/plotting.py
kinetics/ua_and_sa/run_all_models.py
kinetics/ua_and_sa/sampling.py
kinetics/ua_and_sa/sensitivity_analysis.py
kinetics/ua_and_sa/visualise_samples.py
kinetics-1.4.5.dist-info/licenses/LICENSE
kinetics-1.4.5.dist-info/METADATA
kinetics-1.4.5.dist-info/WHEEL
kinetics-1.4.5.dist-info/top_level.txt
kinetics-1.4.5.dist-info/RECORD
