Metadata-Version: 2.4
Name: kinetics
Version: 1.4.5
Summary: Python code to run kinetic models of enzyme reactions
Home-page: https://github.com/willfinnigan/kinetics
Download-URL: https://github.com/willfinnigan/kinetics/archive/1.4.5.tar.gz
Author: William Finnigan
Author-email: wjafinnigan@gmail.com
License: MIT
Keywords: enzyme,kinetics,modelling
Classifier: Development Status :: 3 - Alpha
Classifier: License :: OSI Approved :: MIT License
Classifier: Programming Language :: Python :: 3
License-File: LICENSE
Requires-Dist: scipy
Requires-Dist: numpy
Requires-Dist: SALib
Requires-Dist: tqdm
Requires-Dist: matplotlib
Requires-Dist: pandas
Requires-Dist: deap
Requires-Dist: seaborn
Dynamic: author
Dynamic: author-email
Dynamic: classifier
Dynamic: description
Dynamic: description-content-type
Dynamic: download-url
Dynamic: home-page
Dynamic: keywords
Dynamic: license
Dynamic: license-file
Dynamic: requires-dist
Dynamic: summary
